{
  "modOrganizer": {
    "isUsed": false,
    "pathToMOFolder": "%GAME_DIR%"
  },
  "baseFilesEncoding": "win1251",
  "gameSettingsGroups": [
    {
      "name": "hgD38Xp63Pgq10lO",
      "label": "Audio"
    },
    {
      "name": "7uED7Xd7gPyIIvlu",
      "label": "Graphic"
    }
  ],
  "gameSettingsFiles": [
    {
      "name": "oudf7Xd78FdyIIvaq",
      "label": "OblivionIni",
      "path": "%DOCS_GAME%\\oblivion.ini",
      "view": "sectional",
      "encoding": ""
    }
  ],
  "gameSettingsOptions": [
    {
      "optionType": "combined",
      "file": "oudf7Xd78FdyIIvaq",
      "label": "Разрешение экрана",
      "description": "Устанавливает разрешение экрана",
      "settingGroup": "7uED7Xd7gPyIIvlu",
      "controllerType": "select",
      "separator": ":",
      "selectOptions": {
        "640:480": "640 x 480",
        "800:600": "800 x 600",
        "1024:768": "1024 x 768",
        "1280:720": "1280 x 720",
        "1280:800": "1280 x 800",
        "1280:1024": "1280 x 1024",
        "1366:768": "1366 x 768",
        "1440:900": "1440 x 900",
        "1600:1200": "1600 x 1200",
        "1680:1050": "1680 x 1050",
        "1920:1080": "1920 x 1080",
        "1920:1200": "1920 x 1200",
        "2560:1440": "2560 x 1440",
        "2560:1600": "2560 x 1600",
        "3840:2160": "3840 x 2160"
      },
      "items": [
        {
          "name": "iSize W",
          "iniGroup": "Display"
        },
        {
          "name": "iSize H",
          "iniGroup": "Display"
        }
      ]
    },
    {
      "optionType": "default",
      "file": "oudf7Xd78FdyIIvaq",
      "label": "Громкость музыки",
      "description": "Громкость музыки",
      "settingGroup": "hgD38Xp63Pgq10lO",
      "name": "fDefaultMusicVolume",
      "iniGroup": "Audio",
      "controllerType": "range",
      "min": 0,
      "max": 1,
      "step": 0.1
    }
  ]
}